setup.cfg
setup.py
risotto/__init__.py
risotto/_risotto.c
risotto.egg-info/PKG-INFO
risotto.egg-info/SOURCES.txt
risotto.egg-info/dependency_links.txt
risotto.egg-info/requires.txt
risotto.egg-info/top_level.txt