Metadata-Version: 1.1
Name: risotto
Version: 0.0.3
Summary: Rice aka USES aka SZIP decoder in Python/Cython
Home-page: https://github.com/mraspaud/risotto
Author: Martin Raspaud
Author-email: martin.raspaud@smhi.se
License: UNKNOWN
Platform: UNKNOWN
Classifier: Development Status :: 4 - Beta
Classifier: Intended Audience :: Science/Research
Classifier: License :: OSI Approved :: GNU General Public License v3 or later (GPLv3+)
Classifier: Operating System :: OS Independent
Classifier: Programming Language :: Python
Classifier: Topic :: Scientific/Engineering
Classifier: Topic :: System :: Archiving :: Compression
